kakeibox_controllers/__init__.py
kakeibox_controllers/controllers/__init__.py
kakeibox_controllers/controllers/controller_base.py
kakeibox_controllers/controllers/controller_delete_actions.py
kakeibox_controllers/controllers/controller_get_actions.py
kakeibox_controllers/controllers/controller_list_actions.py
kakeibox_controllers/controllers/controller_list_periods_actions.py
kakeibox_controllers/controllers/controller_new_actions.py
kakeibox_controllers/controllers/controller_update_actions.py
kakeibox_controllers/controllers/transaction_category/__init__.py
kakeibox_controllers/controllers/transaction_category/delete.py
kakeibox_controllers/controllers/transaction_category/get.py
kakeibox_controllers/controllers/transaction_category/list.py
kakeibox_controllers/controllers/transaction_category/new.py
kakeibox_controllers/controllers/transaction_category/update.py
kakeibox_controllers/controllers/transaction_subcategory/__init__.py
kakeibox_controllers/controllers/transaction_subcategory/delete.py
kakeibox_controllers/controllers/transaction_subcategory/get.py
kakeibox_controllers/controllers/transaction_subcategory/list.py
kakeibox_controllers/controllers/transaction_subcategory/list_per_category.py
kakeibox_controllers/controllers/transaction_subcategory/new.py
kakeibox_controllers/controllers/transaction_subcategory/update.py
kakeibox_controllers/handlers/__init__.py
kakeibox_controllers/handlers/kakeibox_executor_handler.py
kakeibox_controllers/handlers/kakeibox_executor_list_handler.py
kakeibox_controllers/handlers/kakeibox_executor_list_periods_handler.py
kakeibox_controllers/handlers/kakeibox_executor_update_handler.py
kakeibox_controllers/handlers/kakeibox_handler.py
kakeibox_controllers/handlers/kakeibox_presenter_handler.py
kakeibox_controllers/handlers/kakeibox_request.py
kakeibox_controllers/handlers/kakeibox_serializer_handler.py
kakeibox_controllers-0.9.4.dist-info/AUTHORS.rst
kakeibox_controllers-0.9.4.dist-info/LICENSE
kakeibox_controllers-0.9.4.dist-info/METADATA
kakeibox_controllers-0.9.4.dist-info/WHEEL
kakeibox_controllers-0.9.4.dist-info/top_level.txt
kakeibox_controllers-0.9.4.dist-info/RECORD
